ConfMerge-0.2.0.dist-info/DESCRIPTION.rst
ConfMerge-0.2.0.dist-info/METADATA
ConfMerge-0.2.0.dist-info/RECORD
ConfMerge-0.2.0.dist-info/WHEEL
ConfMerge-0.2.0.dist-info/entry_points.txt
ConfMerge-0.2.0.dist-info/metadata.json
ConfMerge-0.2.0.dist-info/top_level.txt
ConfMerge-0.2.0.dist-info/zip-safe
confmerge/__init__.py
confmerge/__main__.py
confmerge/cli.py
