Metadata-Version: 2.0
Name: ConfMerge
Version: 0.2.0
Summary: Configuration file merge utility
Home-page: https://github.com/Aisbergg/python-confmerge
Author: Andre Lehmann
Author-email: aisberg@posteo.de
License: LGPL
Project-URL: Bug Reports, https://github.com/Aisbergg/python-confmerge/issues
Project-URL: Source, https://github.com/Aisbergg/python-confmerge
Keywords: config ini yaml json command-line CLI
Platform: POSIX
Classifier: Development Status :: 4 - Beta
Classifier: Environment :: Console
Classifier: Intended Audience :: Developers
Classifier: Intended Audience :: System Administrators
Classifier: License :: OSI Approved :: GNU Lesser General Public License v3 (LGPLv3)
Classifier: Operating System :: POSIX
Classifier: Programming Language :: Python :: 3 :: Only
Classifier: Topic :: System :: Systems Administration
Classifier: Topic :: Utilities
Requires-Dist: pyyaml
